{
  "parentChoices": [
    {
      "Value": 1,
      "Label": "Category A",
      "Color": "#0078D4"
    },
    {
      "Value": 2,
      "Label": "Category B",
      "Color": "#0078D4"
    },
    {
      "Value": 3,
      "Label": "Category C",
      "Color": "#0078D4"
    }
  ],
  "dependentChoices": [
    {"Value": 11, "Label": "Item A1", "Color": "#0078D4"},
    {"Value": 12, "Label": "Item A2", "Color": "#0078D4"},
    {"Value": 13, "Label": "Item A3", "Color": "#0078D4"},
    {"Value": 21, "Label": "Item B1", "Color": "#0078D4"},
    {"Value": 22, "Label": "Item B2", "Color": "#0078D4"},
    {"Value": 23, "Label": "Item B3", "Color": "#0078D4"},
    {"Value": 31, "Label": "Item C1", "Color": "#0078D4"},
    {"Value": 32, "Label": "Item C2", "Color": "#0078D4"},
    {"Value": 33, "Label": "Item C3", "Color": "#0078D4"}
  ]
}
